airflow/providers/teradata/__init__.py
airflow/providers/teradata/get_provider_info.py
airflow/providers/teradata/version_compat.py
airflow/providers/teradata/hooks/__init__.py
airflow/providers/teradata/hooks/bteq.py
airflow/providers/teradata/hooks/teradata.py
airflow/providers/teradata/hooks/tpt.py
airflow/providers/teradata/hooks/ttu.py
airflow/providers/teradata/operators/__init__.py
airflow/providers/teradata/operators/bteq.py
airflow/providers/teradata/operators/teradata.py
airflow/providers/teradata/operators/teradata_compute_cluster.py
airflow/providers/teradata/operators/tpt.py
airflow/providers/teradata/transfers/__init__.py
airflow/providers/teradata/transfers/azure_blob_to_teradata.py
airflow/providers/teradata/transfers/s3_to_teradata.py
airflow/providers/teradata/transfers/teradata_to_teradata.py
airflow/providers/teradata/triggers/__init__.py
airflow/providers/teradata/triggers/teradata_compute_cluster.py
airflow/providers/teradata/utils/__init__.py
airflow/providers/teradata/utils/bteq_util.py
airflow/providers/teradata/utils/constants.py
airflow/providers/teradata/utils/encryption_utils.py
airflow/providers/teradata/utils/tpt_util.py
apache_airflow_providers_teradata-3.4.1.dist-info/entry_points.txt
apache_airflow_providers_teradata-3.4.1.dist-info/licenses/LICENSE
apache_airflow_providers_teradata-3.4.1.dist-info/licenses/NOTICE
apache_airflow_providers_teradata-3.4.1.dist-info/WHEEL
apache_airflow_providers_teradata-3.4.1.dist-info/METADATA
apache_airflow_providers_teradata-3.4.1.dist-info/RECORD
