Metadata-Version: 2.4
Name: apache-airflow-providers-teradata
Version: 3.4.1
Summary: Provider package apache-airflow-providers-teradata for Apache Airflow
Keywords: airflow-provider,teradata,airflow,integration
Author-email: Apache Software Foundation <dev@airflow.apache.org>
Maintainer-email: Apache Software Foundation <dev@airflow.apache.org>
Requires-Python: >=3.10
License-Expression: Apache-2.0
Classifier: Development Status :: 5 - Production/Stable
Classifier: Environment :: Console
Classifier: Environment :: Web Environment
Classifier: Intended Audience :: Developers
Classifier: Intended Audience :: System Administrators
Classifier: Framework :: Apache Airflow
Classifier: Framework :: Apache Airflow :: Provider
Classifier: Programming Language :: Python :: 3.10
Classifier: Programming Language :: Python :: 3.11
Classifier: Programming Language :: Python :: 3.12
Classifier: Programming Language :: Python :: 3.13
Classifier: Topic :: System :: Monitoring
License-File: LICENSE
License-File: NOTICE
Requires-Dist: apache-airflow>=2.11.0
Requires-Dist: apache-airflow-providers-common-compat>=1.12.0
Requires-Dist: apache-airflow-providers-common-sql>=1.20.0
Requires-Dist: teradatasqlalchemy>=17.20.0.0
Requires-Dist: teradatasql>=17.20.0.28
Requires-Dist: apache-airflow-providers-amazon ; extra == "amazon"
Requires-Dist: apache-airflow-providers-microsoft-azure ; extra == "microsoft-azure"
Requires-Dist: sqlalchemy>=1.4.49 ; extra == "sqlalchemy"
Requires-Dist: apache-airflow-providers-ssh ; extra == "ssh"
Project-URL: Bug Tracker, https://github.com/apache/airflow/issues
Project-URL: Changelog, https://airflow.apache.org/docs/apache-airflow-providers-teradata/3.4.1/changelog.html
Project-URL: Documentation, https://airflow.apache.org/docs/apache-airflow-providers-teradata/3.4.1
Project-URL: Mastodon, https://fosstodon.org/@airflow
Project-URL: Slack Chat, https://s.apache.org/airflow-slack
Project-URL: Source Code, https://github.com/apache/airflow
Project-URL: YouTube, https://www.youtube.com/channel/UCSXwxpWZQ7XZ1WL3wqevChA/
Provides-Extra: amazon
Provides-Extra: microsoft-azure
Provides-Extra: sqlalchemy
Provides-Extra: ssh
